package_formula_report_vl-0.0.1.dist-info/licenses/LICENSE
report/__init__.py
report/cli.py
report/formula_report.py
package_formula_report_vl-0.0.1.dist-info/METADATA
package_formula_report_vl-0.0.1.dist-info/WHEEL
package_formula_report_vl-0.0.1.dist-info/entry_points.txt
package_formula_report_vl-0.0.1.dist-info/top_level.txt
package_formula_report_vl-0.0.1.dist-info/RECORD
