Metadata-Version: 2.4
Name: package_formula_report_vl
Version: 0.0.1
Summary: A package for processing log files and generating Formula 1 racing reports
Author-email: Valeriia <valerialisovec606@gmail.com>
License-Expression: MIT
Classifier: Programming Language :: Python :: 3
Classifier: Operating System :: OS Independent
Requires-Python: >=3.9
License-File: LICENSE
Dynamic: license-file
